pyMultiobjective/__init__.py
pyMultiobjective/algorithm/__init__.py
pyMultiobjective/algorithm/c_n_ii.py
pyMultiobjective/algorithm/ctaea.py
pyMultiobjective/algorithm/grea.py
pyMultiobjective/algorithm/hype.py
pyMultiobjective/algorithm/ibea_fc.py
pyMultiobjective/algorithm/ibea_hv.py
pyMultiobjective/algorithm/moead.py
pyMultiobjective/algorithm/n_ii.py
pyMultiobjective/algorithm/n_iii.py
pyMultiobjective/algorithm/naemo.py
pyMultiobjective/algorithm/omopso.py
pyMultiobjective/algorithm/paes.py
pyMultiobjective/algorithm/rvea.py
pyMultiobjective/algorithm/s_ii.py
pyMultiobjective/algorithm/smpso.py
pyMultiobjective/algorithm/sms_emoa.py
pyMultiobjective/algorithm/u_n_iii.py
pyMultiobjective/test_functions/__init__.py
pyMultiobjective/test_functions/mult_many.py
pyMultiobjective/util/__init__.py
pyMultiobjective/util/graphs.py
pyMultiobjective/util/indicators.py
pymultiobjective-1.5.7.dist-info/LICENSE
pymultiobjective-1.5.7.dist-info/METADATA
pymultiobjective-1.5.7.dist-info/WHEEL
pymultiobjective-1.5.7.dist-info/top_level.txt
pymultiobjective-1.5.7.dist-info/RECORD
