Metadata-Version: 2.1
Name: pymultiobjective
Version: 1.5.7
Summary: A python library for Multiobjective Objectives Optimization Algorithms or Many Objectives Optimization Algorithms
Home-page: https://github.com/Valdecy/pyMultiobjective
Author: Valdecy Pereira
Author-email: valdecy.pereira@gmail.com
License: GNU
License-File: LICENSE
Requires-Dist: matplotlib
Requires-Dist: numpy
Requires-Dist: pandas
Requires-Dist: plotly
Requires-Dist: pygmo
Requires-Dist: scipy
